githubsecrets/__init__.py
githubsecrets/__main__.py
githubsecrets/config.py
githubsecrets/ghs.py
githubsecrets/profile.py
githubsecrets/secret.py
githubsecrets-1.0.8.dist-info/LICENSE
githubsecrets-1.0.8.dist-info/METADATA
githubsecrets-1.0.8.dist-info/WHEEL
githubsecrets-1.0.8.dist-info/entry_points.txt
githubsecrets-1.0.8.dist-info/top_level.txt
githubsecrets-1.0.8.dist-info/RECORD
