Metadata-Version: 2.1
Name: githubsecrets
Version: 1.0.8
Summary: A simple CLI to manage GitHub secrets, that are used with GitHub Actions
Home-page: https://github.com/unfor19/githubsecrets
Author: Meir Gabay
Author-email: unfor19@gmail.com
License: MIT
Download-URL: https://github.com/unfor19/githubsecrets/archive/v1.0.8.tar.gz
Keywords: github secrets cli python
Platform: UNKNOWN
Classifier: Development Status :: 5 - Production/Stable
Classifier: Intended Audience :: Developers
Classifier: Topic :: Software Development :: Build Tools
Classifier: License :: OSI Approved :: MIT License
Classifier: Programming Language :: Python :: 3.6
Classifier: Programming Language :: Python :: 3.7
Classifier: Programming Language :: Python :: 3.8
Requires-Dist: Click (>=7.1.1)
Requires-Dist: PyNaCl (>=1.3.0)
Requires-Dist: requests (>=2.23.0)
Requires-Dist: cryptography (>=2.9)
Requires-Dist: keyring (>=21.2.0)
